colorbox/__init__.py
colorbox-0.1.6.dist-info/LICENSE
colorbox-0.1.6.dist-info/METADATA
colorbox-0.1.6.dist-info/WHEEL
colorbox-0.1.6.dist-info/top_level.txt
colorbox-0.1.6.dist-info/RECORD
