Metadata-Version: 2.1
Name: colorbox
Version: 0.1.6
Summary: Color box that provides various colors‘ rgb decimal code.
Home-page: https://github.com/zhangxianbing/colorbox
Author: zhangxianbing
License: MIT License
Keywords: color,bgr,rgb,hex color
Platform: UNKNOWN
Classifier: Development Status :: 3 - Alpha
Classifier: Intended Audience :: Developers
Classifier: License :: OSI Approved :: Apache Software License
Classifier: Programming Language :: Python :: 3.6
Classifier: Programming Language :: Python :: 3.7
Classifier: Programming Language :: Python :: 3.8
Classifier: Programming Language :: Python :: 3.9
Classifier: Programming Language :: Python :: Implementation :: CPython
Requires-Python: >=3.6
License-File: LICENSE
